Metadata-Version: 1.1
Name: bing-web-search-api
Version: 0.0.1
Summary: Client for Bing API v5 Web Search
Home-page: https://github.com/h-kanazawa/bing-web-search-api
Author: h-kanazawa
Author-email: hotaka-kanazawa@dac.co.jp
License: MIT
Keywords: bing
Platform: UNKNOWN
Classifier: Development Status :: 3 - Alpha
Classifier: Intended Audience :: Developers
Classifier: License :: OSI Approved :: MIT License
Classifier: Programming Language :: Python :: 3.5
